Metadata-Version: 2.1
Name: pysimsfar
Version: 1.0.0
Summary: Edit Sims 1 .far files.
Home-page: https://github.com/FaithBeam/pysimsfar
Author: FaithBeam
Author-email: pigeonhopper68@gmail.com
License: MIT
Platform: UNKNOWN
License-File: LICENSE
